{"note":"This file is an internal implementation detail to speed up HTML report generation. Its format can change at any time. You might be looking for the JSON report: https://coverage.rtfd.io/cmd.html#cmd-json","format":5,"version":"7.6.12","globals":"f3a84c4180f2754b32ae926a17a951c4","files":{"z_145eef247bfb46b6___init___py":{"hash":"e6baa73cda2916dad605215f937a92e1","index":{"url":"z_145eef247bfb46b6___init___py.html","file":"src\\__init__.py","description":"","nums":{"precision":0,"n_files":1,"n_statements":0,"n_excluded":0,"n_missing":0,"n_branches":0,"n_partial_branches":0,"n_missing_branches":0}}},"z_145eef247bfb46b6_auxiliary_functions_py":{"hash":"11805747981c0000f020249f5739e452","index":{"url":"z_145eef247bfb46b6_auxiliary_functions_py.html","file":"src\\auxiliary_functions.py","description":"","nums":{"precision":0,"n_files":1,"n_statements":57,"n_excluded":0,"n_missing":8,"n_branches":0,"n_partial_branches":0,"n_missing_branches":0}}},"z_145eef247bfb46b6_base_class_api_py":{"hash":"b39af44e723ece4a95172e8615fbd967","index":{"url":"z_145eef247bfb46b6_base_class_api_py.html","file":"src\\base_class_api.py","description":"","nums":{"precision":0,"n_files":1,"n_statements":8,"n_excluded":0,"n_missing":2,"n_branches":0,"n_partial_branches":0,"n_missing_branches":0}}},"z_145eef247bfb46b6_headhunter_api_py":{"hash":"1f52244fd52da90fc1d36172918a284e","index":{"url":"z_145eef247bfb46b6_headhunter_api_py.html","file":"src\\headhunter_api.py","description":"","nums":{"precision":0,"n_files":1,"n_statements":47,"n_excluded":0,"n_missing":2,"n_branches":0,"n_partial_branches":0,"n_missing_branches":0}}},"z_145eef247bfb46b6_json_saver_py":{"hash":"2593d2d0d6b92b845345ba5d282421fe","index":{"url":"z_145eef247bfb46b6_json_saver_py.html","file":"src\\json_saver.py","description":"","nums":{"precision":0,"n_files":1,"n_statements":61,"n_excluded":0,"n_missing":9,"n_branches":0,"n_partial_branches":0,"n_missing_branches":0}}},"z_145eef247bfb46b6_saving_vacancies_py":{"hash":"4edc1c07e5f1c841978d244c16e5cbc5","index":{"url":"z_145eef247bfb46b6_saving_vacancies_py.html","file":"src\\saving_vacancies.py","description":"","nums":{"precision":0,"n_files":1,"n_statements":0,"n_excluded":0,"n_missing":0,"n_branches":0,"n_partial_branches":0,"n_missing_branches":0}}},"z_145eef247bfb46b6_user_interaction_py":{"hash":"f56be70389eea830f3f1bcc9e4538e21","index":{"url":"z_145eef247bfb46b6_user_interaction_py.html","file":"src\\user_interaction.py","description":"","nums":{"precision":0,"n_files":1,"n_statements":25,"n_excluded":0,"n_missing":25,"n_branches":0,"n_partial_branches":0,"n_missing_branches":0}}},"z_145eef247bfb46b6_vacancy_py":{"hash":"b6b45390035b144ca63895e13e762e4f","index":{"url":"z_145eef247bfb46b6_vacancy_py.html","file":"src\\vacancy.py","description":"","nums":{"precision":0,"n_files":1,"n_statements":46,"n_excluded":0,"n_missing":0,"n_branches":0,"n_partial_branches":0,"n_missing_branches":0}}},"z_145eef247bfb46b6_working_files_py":{"hash":"d4117d0718723f3ea95d0204b4c5ebb5","index":{"url":"z_145eef247bfb46b6_working_files_py.html","file":"src\\working_files.py","description":"","nums":{"precision":0,"n_files":1,"n_statements":0,"n_excluded":0,"n_missing":0,"n_branches":0,"n_partial_branches":0,"n_missing_branches":0}}},"z_145eef247bfb46b6_my_file_py":{"hash":"c5103ede2a1c1f9a810b85a280613418","index":{"url":"z_145eef247bfb46b6_my_file_py.html","file":"src\\my_file.py","description":"","nums":{"precision":0,"n_files":1,"n_statements":0,"n_excluded":0,"n_missing":0,"n_branches":0,"n_partial_branches":0,"n_missing_branches":0}}},"z_145eef247bfb46b6_views_py":{"hash":"0ddf6ca54b22defd74d47e262ffd7857","index":{"url":"z_145eef247bfb46b6_views_py.html","file":"src\\views.py","description":"","nums":{"precision":0,"n_files":1,"n_statements":23,"n_excluded":0,"n_missing":1,"n_branches":0,"n_partial_branches":0,"n_missing_branches":0}}}}}